{"trial_id": "0015", "hyperparameters": {"space": [{"class_name": "Int", "config": {"name": "filters", "default": null, "conditions": [], "min_value": 2, "max_value": 4, "step": 1, "sampling": null}}, {"class_name": "Int", "config": {"name": "units", "default": null, "conditions": [], "min_value": 24, "max_value": 48, "step": 6, "sampling": null}}, {"class_name": "Choice", "config": {"name": "learning_rate", "default": 0.01, "conditions": [], "values": [0.01, 0.001, 0.0001], "ordered": true}}], "values": {"filters": 3, "units": 24, "learning_rate": 0.01, "tuner/epochs": 4, "tuner/initial_epoch": 2, "tuner/bracket": 2, "tuner/round": 1, "tuner/trial_id": "0009"}}, "metrics": {"metrics": {"loss": {"direction": "min", "observations": [{"value": [0.3861866593360901], "step": 0}]}, "SparseCatCrossentropy": {"direction": "min", "observations": [{"value": [0.3840281069278717], "step": 0}]}, "accuracy": {"direction": "max", "observations": [{"value": [0.8617886304855347], "step": 0}]}, "val_loss": {"direction": "min", "observations": [{"value": [0.05233793705701828], "step": 0}]}, "val_SparseCatCrossentropy": {"direction": "min", "observations": [{"value": [0.052312836050987244], "step": 0}]}, "val_accuracy": {"direction": "max", "observations": [{"value": [1.0], "step": 0}]}}}, "score": 0.8617886304855347, "best_step": 0, "status": "COMPLETED"}